setup.py
skylearn/__init__.py
skylearn/biancheng.py
skylearn/panduan.py
skylearn/tiankong.py
skylearn.egg-info/PKG-INFO
skylearn.egg-info/SOURCES.txt
skylearn.egg-info/dependency_links.txt
skylearn.egg-info/top_level.txt