Metadata-Version: 2.1
Name: skylearn
Version: 1.0.1
Summary: DDDD
Home-page: https://www.crotes.top
Author: Crotes
Author-email: 1910546917@qq.com
License: UNKNOWN
Platform: UNKNOWN
Classifier: Programming Language :: Python :: 3
Classifier: License :: OSI Approved :: MIT License
Classifier: Operating System :: OS Independent
